aqueduct/__init__.py
aqueduct/client.py
aqueduct/decorator.py
aqueduct/error.py
aqueduct/flow.py
aqueduct/flow_run.py
aqueduct/github.py
aqueduct/llm_wrapper.py
aqueduct/logger.py
aqueduct/schedule.py
aqueduct/type_annotations.py
aqueduct/artifacts/__init__.py
aqueduct/artifacts/_create.py
aqueduct/artifacts/base_artifact.py
aqueduct/artifacts/bool_artifact.py
aqueduct/artifacts/create.py
aqueduct/artifacts/generic_artifact.py
aqueduct/artifacts/numeric_artifact.py
aqueduct/artifacts/preview.py
aqueduct/artifacts/system_metric.py
aqueduct/artifacts/table_artifact.py
aqueduct/backend/__init__.py
aqueduct/backend/api_client.py
aqueduct/backend/response_helpers.py
aqueduct/constants/__init__.py
aqueduct/constants/enums.py
aqueduct/constants/exports.py
aqueduct/constants/metrics.py
aqueduct/globals/__init__.py
aqueduct/globals/api_client.py
aqueduct/globals/config.py
aqueduct/globals/dag.py
aqueduct/models/__init__.py
aqueduct/models/artifact.py
aqueduct/models/config.py
aqueduct/models/dag.py
aqueduct/models/dag_rules.py
aqueduct/models/execution_state.py
aqueduct/models/operators.py
aqueduct/models/resource.py
aqueduct/models/response_models.py
aqueduct/models/utils.py
aqueduct/resources/__init__.py
aqueduct/resources/airflow.py
aqueduct/resources/aws.py
aqueduct/resources/aws_lambda.py
aqueduct/resources/connect_config.py
aqueduct/resources/databricks.py
aqueduct/resources/dynamic_k8s.py
aqueduct/resources/ecr.py
aqueduct/resources/gar.py
aqueduct/resources/google_sheets.py
aqueduct/resources/k8s.py
aqueduct/resources/mongodb.py
aqueduct/resources/parameters.py
aqueduct/resources/s3.py
aqueduct/resources/salesforce.py
aqueduct/resources/save.py
aqueduct/resources/spark.py
aqueduct/resources/sql.py
aqueduct/resources/validation.py
aqueduct/tests/__init__.py
aqueduct/tests/connect_config_test.py
aqueduct/tests/dag_delta_test.py
aqueduct/tests/dag_test.py
aqueduct/tests/decorator_test.py
aqueduct/tests/decorators_with_without_parentheses_test.py
aqueduct_sdk-0.3.6.dist-info/METADATA
aqueduct_sdk-0.3.6.dist-info/WHEEL
aqueduct_sdk-0.3.6.dist-info/top_level.txt
aqueduct_sdk-0.3.6.dist-info/RECORD
