Metadata-Version: 2.1
Name: aqueduct-sdk
Version: 0.3.6
Summary: Python SDK for Aqueduct
Home-page: https://github.com/aqueducthq/aqueduct
Author: Aqueduct, Inc.
Author-email: hello@aqueducthq.com
License: Apache License 2.0
Classifier: Programming Language :: Python :: 3
Requires-Python: >=3.7
Requires-Dist: setuptools (<=67.2.0)
Requires-Dist: cloudpickle (<=2.2.1)
Requires-Dist: numpy (<=1.24.2)
Requires-Dist: requests (<=2.28.2)
Requires-Dist: pandas (<=1.5.3)
Requires-Dist: IPython (<=8.9.0)
Requires-Dist: croniter (<=1.3.8)
Requires-Dist: pydantic (<=1.10.4,>=1.9.0)
Requires-Dist: plotly (<=5.13.0)
Requires-Dist: pyarrow (<=11.0.0)
Requires-Dist: pyyaml (<=6.0)
Requires-Dist: great-expectations (<=0.15.47)
Requires-Dist: ruamel.yaml (<=0.17.17)
Requires-Dist: Pillow (<=9.4.0)
Requires-Dist: multipart (<=0.2.4)
Requires-Dist: requests-toolbelt (<=0.10.1)
Requires-Dist: pymongo (<=4.3.3)
Requires-Dist: python-dateutil (<=2.8.2)
